photcalib/__init__.py
photcalib/apply_calib.py
photcalib/deform_norm.py
photcalib/make_plots.py
photcalib/model_old.py
photcalib/set_argparse.py
photcalib/training.py
photcalib-0.48.dist-info/LICENSE
photcalib-0.48.dist-info/METADATA
photcalib-0.48.dist-info/WHEEL
photcalib-0.48.dist-info/top_level.txt
photcalib-0.48.dist-info/RECORD
