Metadata-Version: 2.1
Name: photcalib
Version: 0.48
Summary: calibration tool for photometric data
Home-page: https://github.com/zyuan-astro/PhotCalib
Author: Zhen Yuan
Author-email: 
Classifier: Development Status :: 3 - Alpha
Classifier: Intended Audience :: Science/Research
Classifier: Operating System :: OS Independent
Classifier: Programming Language :: Python
Classifier: Topic :: Scientific/Engineering :: Astronomy
License-File: LICENSE
